agtos/__init__.py
agtos/__main__.py
agtos/agents/__init__.py
agtos/agents/base.py
agtos/agents/claude.py
agtos/agents/codex.py
agtos/agents/registry.py
agtos/agents/tool_agent.py
agtos/auth/__init__.py
agtos/auth/client.py
agtos/auth/invite.py
agtos/auth/manager.py
agtos/auth/models.py
agtos/auth/schema.sql
agtos/auth/token.py
agtos/cli/__init__.py
agtos/cli/auth.py
agtos/cli/claude_setup.py
agtos/cli/codex_setup.py
agtos/cli/completion.py
agtos/cli/credentials.py
agtos/cli/diagnostics.py
agtos/cli/export.py
agtos/cli/github.py
agtos/cli/integration.py
agtos/cli/knowledge.py
agtos/cli/launch.py
agtos/cli/mcp_server.py
agtos/cli/mcp_stop.py
agtos/cli/project.py
agtos/cli/run.py
agtos/cli/tutorial.py
agtos/cli/workflow.py
agtos/cli/workflow_updates.py
agtos/cli.py
agtos/completion/__init__.py
agtos/completion/engine.py
agtos/completion/shell.py
agtos/config.py
agtos/context/__init__.py
agtos/context/manager.py
agtos/dev/__init__.py
agtos/dev/interactive.py
agtos/doctor.py
agtos/errors.py
agtos/github_auth.py
agtos/guards/__init__.py
agtos/integrations.py
agtos/knowledge/__init__.py
agtos/knowledge/acquisition.py
agtos/knowledge/api.py
agtos/knowledge/base.py
agtos/knowledge/cli.py
agtos/knowledge/generator.py
agtos/knowledge/intelligent.py
agtos/knowledge/package.py
agtos/knowledge_acquisition.py
agtos/knowledge_store.py
agtos/mcp/__init__.py
agtos/mcp/api.py
agtos/mcp/exporter.py
agtos/mcp/knowledge.py
agtos/mcp/metadata.py
agtos/mcp/templates.py
agtos/mcp/utils.py
agtos/mcp_server.py
agtos/metamcp/__init__.py
agtos/metamcp/aliases/README.md
agtos/metamcp/aliases/__init__.py
agtos/metamcp/aliases/core.py
agtos/metamcp/aliases/custom.py
agtos/metamcp/aliases/learning.py
agtos/metamcp/argument_transformer.py
agtos/metamcp/auth/__init__.py
agtos/metamcp/auth/manager.py
agtos/metamcp/cache/__init__.py
agtos/metamcp/cache/manager.py
agtos/metamcp/cache/strategies.py
agtos/metamcp/categories.py
agtos/metamcp/fuzzy_match.py
agtos/metamcp/hot_reload.py
agtos-0.4.0.dist-info/LICENSE
agtos-0.4.0.dist-info/METADATA
agtos-0.4.0.dist-info/WHEEL
agtos-0.4.0.dist-info/entry_points.txt
agtos-0.4.0.dist-info/RECORD
